sms_store/__init__.py
sms_store/errors.py
sms_store/kma.py
sms_store-1.1.0.dist-info/LICENSE
sms_store-1.1.0.dist-info/METADATA
sms_store-1.1.0.dist-info/WHEEL
sms_store-1.1.0.dist-info/top_level.txt
sms_store-1.1.0.dist-info/RECORD
