Metadata-Version: 2.1
Name: sms-store
Version: 1.1.0
Summary: SMS Store.
Home-page: https://github.com/VisionNetworkProject/python-sms-store
Author: Vision Network
Author-email: michael@vision.network
License: UNKNOWN
Keywords: SMS Store,SMS,Store
Platform: UNKNOWN
Classifier: Programming Language :: Python :: 3
Classifier: License :: OSI Approved :: MIT License
Classifier: Operating System :: OS Independent
Requires-Dist: requests
Requires-Dist: profig
Requires-Dist: cli-print
